{"words": ["The", "player", "won", "five", "games", "in", "a", "row", ".", "Her", "opponent", "felt", "sorry", "for", "her", "."], "verbs": [{"verb": "won", "qa_pairs": [{"question": "Who wond something?", "spans": [{"start": 0, "end": 1, "text": "The player"}]}, {"question": "What did someone won?", "spans": [{"start": 3, "end": 4, "text": "five games"}, {"start": 3, "end": 7, "text": "five games in a row"}]}], "index": 2}, {"verb": "felt", "qa_pairs": [{"question": "Who felted something?", "spans": [{"start": 9, "end": 10, "text": "Her opponent"}]}, {"question": "What did someone felt?", "spans": [{"start": 12, "end": 12, "text": "sorry"}]}, {"question": "Who did someone felt something for?", "spans": [{"start": 14, "end": 14, "text": "her"}]}], "index": 11}]}
