{"words": ["The", "man", "anticipated", "the", "team", "'s", "victory", ".", "He", "met", "his", "friends", "to", "watch", "the", "game", "."], "verbs": [{"verb": "anticipated", "qa_pairs": [{"question": "Who anticipated something?", "spans": [{"start": 0, "end": 1, "text": "The man"}]}, {"question": "What did someone anticipate?", "spans": [{"start": 3, "end": 6, "text": "the team 's victory"}]}], "index": 2}, {"verb": "met", "qa_pairs": [{"question": "Who met someone?", "spans": [{"start": 0, "end": 1, "text": "The man"}, {"start": 8, "end": 8, "text": "He"}]}, {"question": "Who did someone meet?", "spans": [{"start": 10, "end": 11, "text": "his friends"}]}, {"question": "Why did someone meet someone?", "spans": [{"start": 12, "end": 15, "text": "to watch the game"}]}], "index": 9}, {"verb": "watch", "qa_pairs": [{"question": "Who watched something?", "spans": [{"start": 8, "end": 8, "text": "He"}, {"start": 10, "end": 11, "text": "his friends"}]}, {"question": "What did someone watch?", "spans": [{"start": 14, "end": 15, "text": "the game"}]}], "index": 13}]}
