{"words": ["The", "man", "perceived", "that", "the", "woman", "looked", "different", ".", "The", "woman", "got", "her", "hair", "cut", "."], "verbs": [{"verb": "perceived", "qa_pairs": [{"question": "Who perceived something?", "spans": [{"start": 0, "end": 1, "text": "The man"}]}, {"question": "What did someone perceive?", "spans": [{"start": 3, "end": 7, "text": "that the woman looked different"}]}], "index": 2}, {"verb": "looked", "qa_pairs": [{"question": "Who looked?", "spans": [{"start": 4, "end": 5, "text": "the woman"}]}, {"question": "How did someone look?", "spans": [{"start": 7, "end": 7, "text": "different"}]}], "index": 6}, {"verb": "got", "qa_pairs": [{"question": "Who got something?", "spans": [{"start": 9, "end": 10, "text": "The woman"}]}, {"question": "What did someone get?", "spans": [{"start": 12, "end": 14, "text": "her hair cut"}]}], "index": 11}]}
