{"words": ["The", "woman", "became", "famous", ".", "Her", "family", "avoided", "her", "."], "verbs": [{"verb": "became", "qa_pairs": [{"question": "Who became something?", "spans": [{"start": 0, "end": 1, "text": "The woman"}]}, {"question": "What did someone become?", "spans": [{"start": 3, "end": 3, "text": "famous"}]}], "index": 2}, {"verb": "avoided", "qa_pairs": [{"question": "Who avoided someone?", "spans": [{"start": 5, "end": 6, "text": "Her family"}]}, {"question": "Who did someone avoid?", "spans": [{"start": 8, "end": 8, "text": "her"}]}], "index": 7}]}
