{"words": ["The", "girl", "threw", "the", "water", "balloon", "at", "the", "boy", ".", "The", "boy", "got", "soaked", "."], "verbs": [{"verb": "got", "qa_pairs": [{"question": "Who got something?", "spans": [{"start": 10, "end": 11, "text": "The boy"}]}, {"question": "What did someone get?", "spans": [{"start": 13, "end": 13, "text": "soaked"}]}], "index": 12}, {"verb": "soaked", "qa_pairs": [{"question": "Who was soaked?", "spans": [{"start": 10, "end": 11, "text": "The boy"}]}], "index": 13}]}
