{"words": ["The", "boy", "'s", "forehead", "felt", "hot", ".", "His", "mother", "took", "him", "to", "the", "park", "."], "verbs": [{"verb": "felt", "qa_pairs": [{"question": "What felted something?", "spans": [{"start": 0, "end": 3, "text": "The boy 's forehead"}]}, {"question": "What did something felt?", "spans": [{"start": 5, "end": 5, "text": "hot"}]}], "index": 4}, {"verb": "took", "qa_pairs": [{"question": "Who took someone?", "spans": [{"start": 7, "end": 8, "text": "His mother"}]}, {"question": "Who did someone tyek?", "spans": [{"start": 10, "end": 10, "text": "him"}]}, {"question": "Where did someone tyek someone?", "spans": [{"start": 11, "end": 13, "text": "to the park"}]}], "index": 9}]}
