{"words": ["I", "hung", "up", "the", "phone", ".", "The", "caller", "said", "goodbye", "to", "me", "."], "verbs": [{"verb": "hung", "qa_pairs": [{"question": "Who hung up something?", "spans": [{"start": 0, "end": 0, "text": "I"}]}, {"question": "What did someone hang up?", "spans": [{"start": 3, "end": 4, "text": "the phone"}]}], "index": 1}, {"verb": "said", "qa_pairs": [{"question": "Who said something?", "spans": [{"start": 6, "end": 7, "text": "The caller"}]}, {"question": "What did someone say?", "spans": [{"start": 9, "end": 9, "text": "goodbye"}]}, {"question": "Who did someone say something to?", "spans": [{"start": 11, "end": 11, "text": "me"}]}], "index": 8}]}
