{"words": ["The", "runner", "wore", "shorts", ".", "She", "planned", "to", "run", "along", "the", "beach", "."], "verbs": [{"verb": "wore", "qa_pairs": [{"question": "Who wore something?", "spans": [{"start": 0, "end": 1, "text": "The runner"}]}, {"question": "What did someone wear?", "spans": [{"start": 3, "end": 3, "text": "shorts"}]}], "index": 2}, {"verb": "planned", "qa_pairs": [{"question": "Who planned to do something?", "spans": [{"start": 0, "end": 1, "text": "The runner"}, {"start": 5, "end": 5, "text": "She"}]}, {"question": "What did someone plan?", "spans": [{"start": 7, "end": 11, "text": "to run along the beach"}]}, {"question": "What did someone plan to do?", "spans": [{"start": 8, "end": 11, "text": "run along the beach"}]}], "index": 6}, {"verb": "run", "qa_pairs": [{"question": "Who ran somewhere?", "spans": [{"start": 0, "end": 1, "text": "The runner"}, {"start": 5, "end": 5, "text": "She"}]}, {"question": "Where did someone run?", "spans": [{"start": 9, "end": 11, "text": "along the beach"}]}], "index": 8}]}
