{"words": ["The", "woman", "shivered", "as", "she", "got", "out", "the", "pool", ".", "She", "wrapped", "herself", "in", "a", "towel", "."], "verbs": [{"verb": "shivered", "qa_pairs": [{"question": "Who shivered?", "spans": [{"start": 0, "end": 1, "text": "The woman"}]}, {"question": "When did someone shiver?", "spans": [{"start": 3, "end": 8, "text": "as she got out the pool"}]}], "index": 2}, {"verb": "got", "qa_pairs": [{"question": "Who got up something?", "spans": [{"start": 0, "end": 1, "text": "The woman"}, {"start": 4, "end": 4, "text": "she"}]}, {"question": "Where did someone get?", "spans": [{"start": 6, "end": 8, "text": "out the pool"}]}, {"question": "What did someone get up?", "spans": [{"start": 7, "end": 8, "text": "the pool"}]}], "index": 5}, {"verb": "wrapped", "qa_pairs": [{"question": "Who wrapped something?", "spans": [{"start": 0, "end": 1, "text": "The woman"}, {"start": 10, "end": 10, "text": "She"}]}, {"question": "Who did someone wrap?", "spans": [{"start": 12, "end": 12, "text": "herself"}]}, {"question": "Where did someone wrap something?", "spans": [{"start": 13, "end": 15, "text": "in a towel"}]}, {"question": "What did someone wrap someone in?", "spans": [{"start": 14, "end": 15, "text": "a towel"}]}], "index": 11}]}
